MANIFEST.in
README.rst
requirements.txt
setup.py
gsm_modem_asyncio/__init__.py
gsm_modem_asyncio/asyncio_serial_connector.py
gsm_modem_asyncio/client.py
gsm_modem_asyncio/connector.py
gsm_modem_asyncio/exceptions.py
gsm_modem_asyncio/gsm_modem.py
gsm_modem_asyncio/regexp_client.py
gsm_modem_asyncio/serial_protocol.py
gsm_modem_asyncio/tcp_protocol.py
gsm_modem_asyncio.egg-info/PKG-INFO
gsm_modem_asyncio.egg-info/SOURCES.txt
gsm_modem_asyncio.egg-info/dependency_links.txt
gsm_modem_asyncio.egg-info/requires.txt
gsm_modem_asyncio.egg-info/top_level.txt