Metadata-Version: 1.0
Name: gsm-modem-asyncio
Version: 0.1.0
Summary: GSM modem control library
Home-page: https://github.com/insolite/gsm-modem-asyncio
Author: Oleg Krasnikov
Author-email: a.insolite@gmail.com
License: UNKNOWN
Platform: UNKNOWN
